setup.py
aiom3u8/__init__.py
aiom3u8/api.py
aiom3u8/core.py
aiom3u8/ffmpeg.exe
aiom3u8/merge.py
aiom3u8/params_def.py
aiom3u8/parse.py
aiom3u8/session.py
aiom3u8.egg-info/PKG-INFO
aiom3u8.egg-info/SOURCES.txt
aiom3u8.egg-info/dependency_links.txt
aiom3u8.egg-info/requires.txt
aiom3u8.egg-info/top_level.txt